ocm2/__init__.py
ocm2/ocm2.py
ocm2-0.2.0.dist-info/LICENSE
ocm2-0.2.0.dist-info/METADATA
ocm2-0.2.0.dist-info/WHEEL
ocm2-0.2.0.dist-info/dependency_links.txt
ocm2-0.2.0.dist-info/top_level.txt
ocm2-0.2.0.dist-info/RECORD
