Metadata-Version: 2.1
Name: ocm2
Version: 0.2.0
Summary: This python package extracts subdatasets from OCM-2 HDF file, georeference them and exports them to GeoTIFF. The package also creates a cloud mask layer.
Home-page: https://github.com/akhi9661/ocm2
Author: Akhilesh Kumar
Author-email: akhiraj9661@gmail.com
License: MIT license
Keywords: ocm2
Classifier: Development Status :: 2 - Pre-Alpha
Classifier: Intended Audience :: Developers
Classifier: License :: OSI Approved :: MIT License
Classifier: Natural Language :: English
Classifier: Programming Language :: Python :: 3
Classifier: Programming Language :: Python :: 3.7
Classifier: Programming Language :: Python :: 3.8
Classifier: Programming Language :: Python :: 3.9
Classifier: Programming Language :: Python :: 3.10
Requires-Python: >=3.7
License-File: LICENSE
Requires-Dist: numpy
Requires-Dist: rasterio
Requires-Dist: regex
